foobar/__init__.py
foobar3/__init__.py
installable/__init__.py
installable-1.0.dist-info/METADATA
installable-1.0.dist-info/WHEEL
installable-1.0.dist-info/top_level.txt
installable-1.0.dist-info/RECORD
