Metadata-Version: 2.1
Name: installable
Version: 1.0
Summary: A minimal stub package to test success of pip install
Home-page: UNKNOWN
Author: Winson Luk
Author-email: winson.luk@gmail.com
License: MIT
Platform: UNKNOWN
